LICENSE
README.md
setup.py
slinn/__init__.py
slinn/__main__.py
slinn/address.py
slinn/any_filter.py
slinn/dispatcher.py
slinn/file.py
slinn/filter.py
slinn/http_api_response.py
slinn/http_json_api_response.py
slinn/http_json_response.py
slinn/http_redirect.py
slinn/http_response.py
slinn/link_filter.py
slinn/request.py
slinn/server.py
slinn/utils.py
slinn.egg-info/PKG-INFO
slinn.egg-info/SOURCES.txt
slinn.egg-info/dependency_links.txt
slinn.egg-info/top_level.txt
slinn.egg-info/zip-safe
slinn/default/__init__.py
slinn/default/manage.py
slinn/default/project.json
slinn/guides/__init__.py
slinn/guides/migration1xx2xx.py
slinn/templates/__init__.py
slinn/templates/example/__init__.py
slinn/templates/example/app.py
slinn/templates/example/config.json
slinn/templates/firstrun/__init__.py
slinn/templates/firstrun/app.py
slinn/templates/firstrun/config.json
slinn/templates/firstrun/data/slinn.html
slinn/templates/firstrun/data/styles.css