Metadata-Version: 2.1
Name: slinn
Version: 2.2.13
Summary: A HTTPS and HTTP server framework
Home-page: https://slinn.miotp.ru/
Author: Mark Radin
Author-email: mrybs2@gmail.com
Requires-Python: >=3.11
License-File: LICENSE
